cli/__init__.py
cli/auth.py
cli/config.py
cli/main.py
cli/utils.py
cli/assessment_client/__init__.py
cli/assessment_client/client.py
cli/commands/__init__.py
cli/commands/agent.py
cli/commands/assessment.py
cli/commands/assessment_finding.py
cli/commands/assessment_job.py
cli/commands/assessment_session.py
cli/commands/asset.py
cli/commands/bookmark.py
cli/commands/credential.py
cli/commands/document.py
cli/commands/documents.py
cli/commands/event.py
cli/commands/export.py
cli/commands/framework.py
cli/commands/grep.py
cli/commands/ingestion.py
cli/commands/job.py
cli/commands/knowledge_space.py
cli/commands/login.py
cli/commands/logs.py
cli/commands/read.py
cli/commands/reingest.py
cli/commands/search.py
cli/commands/upload.py
cli/commands/user.py
cli/knowledge_base_client/__init__.py
cli/knowledge_base_client/auth.py
cli/knowledge_base_client/client.py
kosmos_cli-0.2.1.dist-info/METADATA
kosmos_cli-0.2.1.dist-info/WHEEL
kosmos_cli-0.2.1.dist-info/entry_points.txt
kosmos_cli-0.2.1.dist-info/top_level.txt
kosmos_cli-0.2.1.dist-info/RECORD
